{
   "post_detail":{
      "detail_name":"portfolio/brand_integration_reel",
      "filename":"BrandIntegrationReelFINAL",
      "related_posts":[

      ],
      "client":"",
      "related_links":[

      ],
      "description":"View our brand integration reel.",
      "title":"Brand Integration Reel",
      "assets":[
         {
            "id":"1",
            "description":"",
            "filename":"BrandIntegrationReelFINAL",
            "title":"",
            "media_type":"1"
         }
      ]
   }
}