{
   "post_detail":{
      "related_posts":[

      ],
      "assets":[
         {
            "id":"1",
            "description":"",
            "media_type":"1",
            "title":"",
            "filename":"FishboneAnimation"
         }
      ],
      "related_links":[

      ],
      "client":"",
      "description":"We created the flat 2D artwork in Photo Shop and composited them in After Effects.",
      "detail_name":"portfolio/fishbone",
      "title":"Fishbone",
      "filename":"FishboneAnimation"
   }
}