{
   "post_detail":{
      "related_posts":[

      ],
      "assets":[
         {
            "id":"1",
            "description":"",
            "media_type":"1",
            "title":"",
            "filename":"12954_Solange_I_DECIDED"
         }
      ],
      "related_links":[

      ],
      "client":"Solange",
      "description":"Using provided live action green screen footage of Solange, we created animated backgrounds and composited it all in Flame.",
      "detail_name":"portfolio/i_decided",
      "title":"I Decided",
      "filename":"12954_Solange_I_DECIDED"
   }
}