{
   "post_detail":{
      "detail_name":"portfolio/visa_metal_detector",
      "filename":"JeremyVisa_MetalDetector",
      "related_posts":[

      ],
      "client":"",
      "related_links":[

      ],
      "description":"Click 3X Editor Jeremy Baumann edited this spot.",
      "title":"Visa Metal Detector",
      "assets":[
         {
            "id":"1",
            "description":"",
            "filename":"JeremyVisa_MetalDetector",
            "title":"",
            "media_type":"1"
         }
      ]
   }
}