{
   "post_detail":{
      "related_posts":[

      ],
      "assets":[
         {
            "id":"1",
            "description":"",
            "media_type":"1",
            "title":"",
            "filename":"MTV_Lady_Gaga_VMA_2011"
         }
      ],
      "related_links":[

      ],
      "client":"",
      "description":"Using provided live action footage and various sparks in Flame, we created this promo for the VMA Awards.",
      "detail_name":"portfolio/ladygaga",
      "title":"Lady Gaga",
      "filename":"MTV_Lady_Gaga_VMA_2011"
   }
}